sopel_modules/__init__.py
sopel_modules/genius-answer/__init__.py
sopel_modules.genius_answer-0.0.21.dist-info/METADATA
sopel_modules.genius_answer-0.0.21.dist-info/WHEEL
sopel_modules.genius_answer-0.0.21.dist-info/top_level.txt
sopel_modules.genius_answer-0.0.21.dist-info/RECORD
