Metadata-Version: 2.1
Name: sopel_modules.genius-answer
Version: 0.0.21
Summary: A sopel plugin (irc-bot) to answer with a quote from rapgenius.com 
Author-email: eoli3n <eoli3n@runbox.com>
License: WTFPL
Project-URL: Source code, https://github.com/eoli3n/sopel-genius-answer
Requires-Python: >=3.8
Requires-Dist: sopel <8,>=7.1
Requires-Dist: lyricsgenius <4,>=3.0.1
